heimer_tools/HeimerMap.py
heimer_tools/__init__.py
heimer_tools/convert.py
heimer_tools/make_dot.py
heimer_tools/reader.py
heimer_tools/writer.py
heimer_tools-0.1b1.dist-info/LICENSE
heimer_tools-0.1b1.dist-info/METADATA
heimer_tools-0.1b1.dist-info/WHEEL
heimer_tools-0.1b1.dist-info/entry_points.txt
heimer_tools-0.1b1.dist-info/top_level.txt
heimer_tools-0.1b1.dist-info/RECORD
