Metadata-Version: 2.1
Name: heimer-tools
Version: 0.1b1
Summary: Create dot files from files generated by heimer
Home-page: https://github.com/romilly/heimer-tools
Author: Romilly Cocking
Author-email: romilly.cocking@gmail.com
Project-URL: Bug Tracker, https://github.com/romilly/heimer-tools/issues
Classifier: Programming Language :: Python :: 3
Classifier: License :: OSI Approved :: MIT License
Classifier: Operating System :: OS Independent
Requires-Python: >=3.8
License-File: LICENSE
Requires-Dist: graphviz
